[
    {
        "idErp": "053135481000109",
        "corporateName": "LICIA CIBELE OLIVEIRA LOURENCO",
        "pricingTable": {
            "b2b": false,
            "defaultAtCustomerCreation": true,
            "description": "",
            "discount": 0,
            "email": "",
            "enabled": true,
            "idErp": "",
            "maxDiscount": 0,
            "name": ""
        },
        "b2bCashbackPercent": 0,
        "b2bMinOrderValue": 0,
        "b2bPricingTableId": 0,
        "billingAddress": {
            "city": "ICO",
            "country": "Brasil",
            "district": "",
            "idErp": "053135481000109",
            "number": "308       ",
            "state": "CE",
            "street": "RUA SAO SEBASTIAO",
            "zip": "63430-000"
        },
        "birthDate": "",
        "blocked": false,
        "cashbackBalanceAvailable": 0,
        "cashbackBalancePending": 0,
        "cashbackPercent": 0,
        "code": "053135481000109",
        "creationTime": "",
        "creditLimit": 500,
        "creditUsedValue": 0,
        "email": "cibelelourenco123@gmail.com",
        "extras": {},
        "fax": "",
        "federalId": "53.135.481/0001-09",
        "filiation": "",
        "inscricaoEstadual": "071651888       ",
        "minOrderValue": 0,
        "name": "EMPORIO LOURENC",
        "notes": "",
        "paymentFormsIds": "",
        "paymentFormsIdsErp": "",
        "paymentTermsIds": "",
        "paymentTermsIdsErp": "1,60,61,62",
        "phone": "88993537125",
        "pipelineRemoved": true,
        "ponderedAverageDelayValue": 0,
        "ponderedIndexDelayValue": 0,
        "rg": "",
        "salesmanName": "",
        "shippingAddress": {
            "city": "ICO",
            "country": "Brasil",
            "district": "",
            "idErp": "053135481000109",
            "number": "308       ",
            "state": "CE",
            "street": "RUA SAO SEBASTIAO",
            "zip": "63430-000"
        },
        "status": 2,
        "suframa": ""
    }
]